LICENSE.md
README.md
setup.py
debyetools/XS.py
debyetools/__init__.py
debyetools/anharmonicity.py
debyetools/aux_functions.py
debyetools/debfunct.py
debyetools/defects.py
debyetools/electronic.py
debyetools/fs_compound_db.py
debyetools/get_elastic.py
debyetools/load_data_from_DFT.py
debyetools/ndeb.py
debyetools/optim.py
debyetools/pairanalysis.py
debyetools/poisson.py
debyetools/potentials.py
debyetools/vibrational.py
debyetools.egg-info/PKG-INFO
debyetools.egg-info/SOURCES.txt
debyetools.egg-info/dependency_links.txt
debyetools.egg-info/requires.txt
debyetools.egg-info/top_level.txt
debyetools/examples/__init__.py
debyetools/examples/Al3Li_L12/CONTCAR
debyetools/examples/Al3Li_L12/DOSCAR.EvV.01
debyetools/examples/Al3Li_L12/DOSCAR.EvV.02
debyetools/examples/Al3Li_L12/DOSCAR.EvV.03
debyetools/examples/Al3Li_L12/DOSCAR.EvV.04
debyetools/examples/Al3Li_L12/DOSCAR.EvV.05
debyetools/examples/Al3Li_L12/DOSCAR.EvV.06
debyetools/examples/Al3Li_L12/DOSCAR.EvV.07
debyetools/examples/Al3Li_L12/DOSCAR.EvV.08
debyetools/examples/Al3Li_L12/DOSCAR.EvV.09
debyetools/examples/Al3Li_L12/DOSCAR.EvV.10
debyetools/examples/Al3Li_L12/DOSCAR.EvV.11
debyetools/examples/Al3Li_L12/DOSCAR.EvV.12
debyetools/examples/Al3Li_L12/DOSCAR.EvV.13
debyetools/examples/Al3Li_L12/DOSCAR.EvV.14
debyetools/examples/Al3Li_L12/DOSCAR.EvV.15
debyetools/examples/Al3Li_L12/DOSCAR.EvV.16
debyetools/examples/Al3Li_L12/DOSCAR.EvV.17
debyetools/examples/Al3Li_L12/DOSCAR.EvV.18
debyetools/examples/Al3Li_L12/DOSCAR.EvV.19
debyetools/examples/Al3Li_L12/DOSCAR.EvV.20
debyetools/examples/Al3Li_L12/DOSCAR.EvV.21
debyetools/examples/Al3Li_L12/OUTCAR_elastic
debyetools/examples/Al3Li_L12/SUMMARY
debyetools/examples/Al_fcc/CONTCAR
debyetools/examples/Al_fcc/DOSCAR.EvV.01
debyetools/examples/Al_fcc/DOSCAR.EvV.02
debyetools/examples/Al_fcc/DOSCAR.EvV.03
debyetools/examples/Al_fcc/DOSCAR.EvV.04
debyetools/examples/Al_fcc/DOSCAR.EvV.05
debyetools/examples/Al_fcc/DOSCAR.EvV.06
debyetools/examples/Al_fcc/DOSCAR.EvV.07
debyetools/examples/Al_fcc/DOSCAR.EvV.08
debyetools/examples/Al_fcc/DOSCAR.EvV.09
debyetools/examples/Al_fcc/DOSCAR.EvV.10
debyetools/examples/Al_fcc/DOSCAR.EvV.11
