Metadata-Version: 2.2
Name: debyetools
Version: 2.7.5
Summary: Debye approximation implementation for the calculation of thermodynamic properties from ground-state atomistic simulations.
Home-page: https://debyetools.readthedocs.io/
Author: Javier Jofre
Author-email: javier.jofre@polymtl.ca
License: GPLv3
Classifier: Intended Audience :: Developers
Classifier: License :: OSI Approved :: GNU Affero General Public License v3
Classifier: Programming Language :: Python
Classifier: Programming Language :: Python :: 3.10
Classifier: Programming Language :: Python :: 3.12
Classifier: Operating System :: OS Independent
License-File: LICENSE.md
Requires-Dist: numpy
Requires-Dist: scipy
Requires-Dist: matplotlib
Requires-Dist: mpmath
Requires-Dist: PySide6
Requires-Dist: deap
Dynamic: author
Dynamic: author-email
Dynamic: classifier
Dynamic: description
Dynamic: description-content-type
Dynamic: home-page
Dynamic: license
Dynamic: requires-dist
Dynamic: summary
